pynvim_python_interpreter/__init__.py
pynvim_python_interpreter-1.0.0.dist-info/METADATA
pynvim_python_interpreter-1.0.0.dist-info/WHEEL
pynvim_python_interpreter-1.0.0.dist-info/entry_points.txt
pynvim_python_interpreter-1.0.0.dist-info/RECORD
