Metadata-Version: 2.4
Name: pynvim-python-interpreter
Version: 1.0.0
Summary: Neovim pynvim python executable wrapper
Author-email: Michael Henry <drmikehenry@drmikehenry.com>
Requires-Python: >=3.8
Requires-Dist: pynvim>=0.5.2
